LICENSE
README.rst
setup.py
sponge_test/__init__.py
sponge_test/__main__.py
sponge_test/test_installation.py
sponge_test/test_meta1d.py
sponge_test/test_minimization.py
sponge_test/test_rmsd.py
sponge_test/test_sits.py
sponge_test/test_thermostat.py
sponge_test/test_umbrella.py
sponge_test.egg-info/PKG-INFO
sponge_test.egg-info/SOURCES.txt
sponge_test.egg-info/dependency_links.txt
sponge_test.egg-info/entry_points.txt
sponge_test.egg-info/requires.txt
sponge_test.egg-info/top_level.txt
sponge_test/H2O2/H2O2_LJ.txt
sponge_test/H2O2/H2O2_angle.txt
sponge_test/H2O2/H2O2_bond.txt
sponge_test/H2O2/H2O2_charge.txt
sponge_test/H2O2/H2O2_coordinate.txt
sponge_test/H2O2/H2O2_dihedral.txt
sponge_test/H2O2/H2O2_exclude.txt
sponge_test/H2O2/H2O2_mass.txt
sponge_test/H2O2/H2O2_nb14.txt
sponge_test/H2O2/H2O2_residue.txt
sponge_test/H2O2/__init__.py
sponge_test/ala12/__init__.py
sponge_test/ala12/ala12_LJ.txt
sponge_test/ala12/ala12_angle.txt
sponge_test/ala12/ala12_bond.txt
sponge_test/ala12/ala12_charge.txt
sponge_test/ala12/ala12_coordinate.txt
sponge_test/ala12/ala12_dihedral.txt
sponge_test/ala12/ala12_exclude.txt
sponge_test/ala12/ala12_gb.txt
sponge_test/ala12/ala12_mass.txt
sponge_test/ala12/ala12_nb14.txt
sponge_test/ala12/ala12_residue.txt
sponge_test/bad_dipeptide/__init__.py
sponge_test/bad_dipeptide/dipeptide.mol2
sponge_test/bad_dipeptide/dipeptide_LJ.txt
sponge_test/bad_dipeptide/dipeptide_angle.txt
sponge_test/bad_dipeptide/dipeptide_bond.txt
sponge_test/bad_dipeptide/dipeptide_charge.txt
sponge_test/bad_dipeptide/dipeptide_coordinate.txt
sponge_test/bad_dipeptide/dipeptide_dihedral.txt
sponge_test/bad_dipeptide/dipeptide_exclude.txt
sponge_test/bad_dipeptide/dipeptide_mass.txt
sponge_test/bad_dipeptide/dipeptide_nb14.txt
sponge_test/bad_dipeptide/dipeptide_residue.txt
sponge_test/bad_water/__init__.py
sponge_test/bad_water/water_LJ.txt
sponge_test/bad_water/water_bond.txt
sponge_test/bad_water/water_charge.txt
sponge_test/bad_water/water_coordinate.txt
sponge_test/bad_water/water_exclude.txt
sponge_test/bad_water/water_mass.txt
sponge_test/bad_water/water_residue.txt
sponge_test/dipeptide/__init__.py
sponge_test/dipeptide/dipeptide.mol2
